{
  "metadata": {
    "timestamp": "2025-07-27T18:15:03.534464",
    "simulator_type": "LoKISimulator",
    "setup_file": "setup_O2_simple.in",
    "chem_file": "O2_simple_1.chem",
    "loki_path": "C:\\MyPrograms\\LoKI_v3.1.0-v2",
    "execution_time_seconds": 37.234525,
    "simulation_hash": "c00654fed0c4",
    "n_simulations": 5,
    "n_k_varied": 3,
    "n_species": 3,
    "k_columns_varied": [
      0,
      1,
      2
    ],
    "reference_k_values": [
      6e-16,
      1.3e-15,
      9.6e-16,
      2.2e-15,
      7e-22,
      3e-44,
      3.2e-45,
      5.2,
      53.0
    ],
    "loki_version": "v3.1.0",
    "chemistry": "O2_simple"
  },
  "inputs": {
    "k_values": [
      [
        4.594900438756178e-16,
        1.1764764419980527e-15,
        1.083745108815238e-15
      ],
      [
        5.202414937938067e-16,
        1.5916536907288588e-15,
        9.833501127562507e-16
      ],
      [
        6.295021172745635e-16,
        1.0092504610163316e-15,
        9.696446277873391e-16
      ],
      [
        7.034674505426375e-16,
        1.3090571050107365e-15,
        8.079869319609674e-16
      ],
      [
        5.796902597603946e-16,
        1.377084783137446e-15,
        7.615519624772868e-16
      ]
    ],
    "k_shape": [
      5,
      3
    ]
  },
  "outputs": {
    "compositions": [
      [
        "1.08142339205192e+23",
        "2.56040209511148e+21",
        "1.73774551086585e+22"
      ],
      [
        "1.08838822183618e+23",
        "2.99121912911134e+21",
        "1.62499986645698e+22"
      ],
      [
        "1.08145112953692e+23",
        "3.73406201492214e+21",
        "1.62008480484585e+22"
      ],
      [
        "1.09234534183959e+23",
        "4.51170201472830e+21",
        "1.43336009283651e+22"
      ],
      [
        "1.10599817790325e+23",
        "3.86159708594513e+21",
        "1.36183755790941e+22"
      ]
    ],
    "composition_shape": [
      5,
      3
    ]
  }
}